HW1/1_comparator-SeanSurface - Copy.v
/*************************************************
*	Sean Webster
*	ADSD - Summer 2016 - Martin Margala
*	Homework 1
*
*	1_comparator.v				
*
*	A single 1 bit comparator comprised of 2 inverters 
*	and 3 NAND gates
*	
*	2 inputs: 	A and B
*	3 outputs:	
**************************************************/

module comparator_1(A, B, L, E, G);
	input A, B;	// 2 bits to be compared
	output L, E, G;	//
	wire s1, s2;

	not X1(s1, A);
	not X2 (s2, B);
	nand X3 (G, s1, B);
	nand X4 (L, s2, A);
	nand X5 (E, L, G);


endmodule

HW1/comparator_4_copy.v
/*************************************************
*	Sean Webster
*	ADSD - Summer 2016 - Martin Margala
*	Homework 1
*
*	comparator_4.v				
* 
*	4 chained 1 bit comparators
*	
*	based on schematic for MC14585B	
*		http://onsemi.com
**************************************************/

module comparator_4(Lo, Eo, Go, A, B, Li, Ei, Gi);
	input [3:0] A; input [3:0] B; 	//4 bit inputs 
	input Li, Gi, Ei;		//A<B, A=B, A>B inputs
	output Lo, Go, Eo;		//A<B, A=B, A>B outputs from chip
	wire [3:0]L; wire [3:0]E; wire [3:0]G;	//A<B, A=B, A>B outputs from individual comparators
	wire s0, s1, s2, s3, s4, s5, s6, s7, s8;

	// Set up individual 1 bit converters	
	comparator_1 comp0(A[0], B[0], L[0], E[0], G[0]);
	comparator_1 comp1(A[1], B[1], L[1], E[1], G[1]);
	comparator_1 comp2(A[2], B[2], L[2], E[2], G[2]);
	comparator_1 comp3(A[3], B[3], L[3], E[3], G[3]);

	// Gate logic from schematic
	
	or X1(s3, E[3], L[2]);
	or X2(s2, E[3], E[2], L[1]);
	or X3(s1, E[3], E[2], E[1], L[0]);
	or X4(s0, E[3], E[2], E[1], E[0], ~Li);
	nor X5(s4, E[3], E[2], E[1], E[0], ~Ei);
	nand X6(s5, L[3], s0, s1, s2, s3);
	nor X7(Go, s5, s4);
	
	
	assign Eo = s4;
	assign Lo = s5;

endmodule

comp4_tb.v
/*************************************************
*	Sean Webster
*	ADSD - Summer 2016 - Martin Margala
*	Homework 1
*
*	comparator_4.v				
* 
*	test bench for 4 bit comparator
*	
*	based on schematic for MC14585B	
*		http://onsemi.com
**************************************************/
module comp4_tb;
	reg [3:0]A; reg [3:0]B;
	wire Lo, Eo, Go;

	comparator_4 comp4(Lo, Eo, Go, A, B, 0, 1, 0);

	
	integer i, j = 4'b0;
	initial begin
	
		$dumpfile("test.vcd");		// create log file
		$dumpvars(0, comp4_tb);

		// Generate test numbers for A and B
		A = 0;
		B = 0;
		for(i= 0; i < 8; i = i +1) begin
			A = i;	# 10;
			for(j = 0; j < 8; j = j +1) begin
				B = j;	#10;
			end
		end
	end

	initial		// Output to console 
		$monitor("At time %2t, A = %u B = %u L = %d E = %d G = %d",
				$time, A, B, Lo, Eo, Go);
				

endmodule

HW1/test.vcd
$date
	Wed Jul 27 16:12:20 2016
$end
$version
	ModelSim Version 10.4a
$end
$timescale
	1ns
$end

$scope module comp4_tb $end
$var reg 4 ! A [3:0] $end
$var reg 4 " B [3:0] $end
$var wire 1 # Lo $end
$var wire 1 $ Eo $end
$var wire 1 % Go $end
$var integer 32 & i $end
$var integer 32 ' j $end

$scope module comp4 $end
$var wire 1 ( A [3] $end
$var wire 1 ) A [2] $end
$var wire 1 * A [1] $end
$var wire 1 + A [0] $end
$var wire 1 , B [3] $end
$var wire 1 - B [2] $end
$var wire 1 . B [1] $end
$var wire 1 / B [0] $end
$var wire 1 0 Li $end
$var wire 1 1 Gi $end
$var wire 1 2 Ei $end
$var wire 1 # Lo $end
$var wire 1 % Go $end
$var wire 1 $ Eo $end
$var wire 1 3 L [3] $end
$var wire 1 4 L [2] $end
$var wire 1 5 L [1] $end
$var wire 1 6 L [0] $end
$var wire 1 7 E [3] $end
$var wire 1 8 E [2] $end
$var wire 1 9 E [1] $end
$var wire 1 : E [0] $end
$var wire 1 ; G [3] $end
$var wire 1 < G [2] $end
$var wire 1 = G [1] $end
$var wire 1 > G [0] $end
$var wire 1 ? s0 $end
$var wire 1 @ s1 $end
$var wire 1 A s2 $end
$var wire 1 B s3 $end
$var wire 1 C s4 $end
$var wire 1 D s5 $end
$var wire 1 E s6 $end
$var wire 1 F s7 $end
$var wire 1 G s8 $end

$scope module comp0 $end
$var wire 1 + A $end
$var wire 1 / B $end
$var wire 1 6 L $end
$var wire 1 : E $end
$var wire 1 > G $end
$var wire 1 H s1 $end
$var wire 1 I s2 $end
$upscope $end

$scope module comp1 $end
$var wire 1 * A $end
$var wire 1 . B $end
$var wire 1 5 L $end
$var wire 1 9 E $end
$var wire 1 = G $end
$var wire 1 J s1 $end
$var wire 1 K s2 $end
$upscope $end

$scope module comp2 $end
$var wire 1 ) A $end
$var wire 1 - B $end
$var wire 1 4 L $end
$var wire 1 8 E $end
$var wire 1 < G $end
$var wire 1 L s1 $end
$var wire 1 M s2 $end
$upscope $end

$scope module comp3 $end
$var wire 1 ( A $end
$var wire 1 , B $end
$var wire 1 3 L $end
$var wire 1 7 E $end
$var wire 1 ; G $end
$var wire 1 N s1 $end
$var wire 1 O s2 $end
$upscope $end
$upscope $end
$upscope $end
$enddefinitions $end
#0
$dumpvars
b0 !
b0 "
b0 &
b0 '
0#
1$
0%
16
15
14
13
0:
09
08
07
1>
1=
1<
1;
1?
1@
1A
1B
1C
0D
zE
zF
zG
1H
1I
1J
1K
1L
1M
1N
1O
01
12
00
0/
0.
0-
0,
0+
0*
0)
0(
$end
#20
b1 '
b1 "
1/
06
0I
0@
1:
1D
0C
1#
0$
#30
b10 '
b10 "
0/
1.
16
1I
05
0K
1@
0:
0A
19
#40
b11 '
b11 "
1/
06
0I
1:
#50
b100 '
b100 "
0/
0.
1-
16
1I
15
1K
04
0M
0:
1A
09
0B
18
#60
b101 '
b101 "
1/
06
0I
1:
#70
b110 '
b110 "
0/
1.
16
1I
05
0K
0:
19
#80
b111 '
b111 "
1/
06
0I
1:
#90
b1000 '
b1 &
b1 !
1+
0H
16
0:
#100
b0 '
b0 "
0/
0.
0-
1I
15
1K
14
1M
0>
09
1B
08
1:
1C
0D
0C
1$
0#
0$
1%
#110
b1 '
b1 "
1/
0I
1>
0:
1C
1$
0%
#120
b10 '
b10 "
0/
1.
1I
05
0K
0>
0A
19
1:
1D
0C
1#
0$
#130
b11 '
b11 "
1/
0I
1>
0:
#140
b100 '
b100 "
0/
0.
1-
1I
15
1K
04
0M
0>
1A
09
0B
18
1:
#150
b101 '
b101 "
1/
0I
1>
0:
#160
b110 '
b110 "
0/
1.
1I
05
0K
0>
19
1:
#170
b111 '
b111 "
1/
0I
1>
0:
#180
b1000 '
b10 &
b10 !
0+
1*
1H
0J
06
15
1:
09
#190
b0 '
b0 "
0/
0.
0-
16
1I
1K
14
1M
0:
0=
1B
08
1C
19
0D
1$
0C
0#
0$
1%
#200
b1 '
b1 "
1/
06
0I
1:
#210
b10 '
b10 "
0/
1.
16
1I
0K
0:
1=
09
1C
1$
0%
#220
b11 '
b11 "
1/
06
0I
0@
1:
1D
0C
1#
0$
#230
b100 '
b100 "
0/
0.
1-
16
1I
1K
04
0M
1@
0:
0=
0B
18
19
#240
b101 '
b101 "
1/
06
0I
1:
#250
b110 '
b110 "
0/
1.
16
1I
0K
0:
1=
09
#260
b111 '
b111 "
1/
06
0I
1:
#270
b1000 '
b11 &
b11 !
1+
0H
16
0:
#280
b0 '
b0 "
0/
0.
0-
1I
1K
14
1M
0>
0=
1B
08
1:
19
0D
1C
0C
0#
1$
0$
1%
#290
b1 '
b1 "
1/
0I
1>
0:
#300
b10 '
b10 "
0/
1.
1I
0K
0>
1=
1:
09
#310
b11 '
b11 "
1/
0I
1>
0:
1C
1$
0%
#320
b100 '
b100 "
0/
0.
1-
1I
1K
04
0M
0>
0=
0B
18
1:
19
1D
0C
1#
0$
#330
b101 '
b101 "
1/
0I
1>
0:
#340
b110 '
b110 "
0/
1.
1I
0K
0>
1=
1:
09
#350
b111 '
b111 "
1/
0I
1>
0:
#360
b1000 '
b100 &
b100 !
0+
0*
1)
1H
1J
0L
06
05
14
1:
19
1B
08
0D
0A
0#
1%
1D
1#
0%
#370
b0 '
b0 "
0/
0.
0-
16
1I
15
1K
1M
0:
1A
09
0<
1C
0D
18
1$
0#
0C
0$
1%
#380
b1 '
b1 "
1/
06
0I
1:
#390
b10 '
b10 "
0/
1.
16
1I
05
0K
0:
19
#400
b11 '
b11 "
1/
06
0I
1:
#410
b100 '
b100 "
0/
0.
1-
16
1I
15
1K
0M
0:
09
1<
08
1C
1$
0%
#420
b101 '
b101 "
1/
06
0I
0@
1:
1D
0C
1#
0$
#430
b110 '
b110 "
0/
1.
16
1I
05
0K
1@
0:
0A
19
#440
b111 '
b111 "
1/
06
0I
1:
#450
b1000 '
b101 &
b101 !
1+
0H
16
0:
#460
b0 '
b0 "
0/
0.
0-
1I
15
1K
1M
0>
1A
09
0<
1:
0D
1C
18
0C
0#
1$
0$
1%
#470
b1 '
b1 "
1/
0I
1>
0:
#480
b10 '
b10 "
0/
1.
1I
05
0K
0>
19
1:
#490
b11 '
b11 "
1/
0I
1>
0:
#500
b100 '
b100 "
0/
0.
1-
1I
15
1K
0M
0>
09
1<
1:
08
#510
b101 '
b101 "
1/
0I
1>
0:
1C
1$
0%
#520
b110 '
b110 "
0/
1.
1I
05
0K
0>
0A
19
1:
1D
0C
1#
0$
#530
b111 '
b111 "
1/
0I
1>
0:
#540
b1000 '
b110 &
b110 !
0+
1*
1H
0J
06
15
1:
1A
09
0D
0@
0#
1%
1D
1#
0%
#550
b0 '
b0 "
0/
0.
0-
16
1I
1K
1M
1@
0:
0=
0<
0D
1C
19
18
0#
1$
0C
0$
1%
#560
b1 '
b1 "
1/
06
0I
1:
#570
b10 '
b10 "
0/
1.
16
1I
0K
0:
1=
09
#580
b11 '
b11 "
1/
06
0I
1:
#590
b100 '
b100 "
0/
0.
1-
16
1I
1K
0M
0:
0=
1<
19
08
#600
b101 '
b101 "
1/
06
0I
1:
#610
b110 '
b110 "
0/
1.
16
1I
0K
0:
1=
09
1C
1$
0%
#620
b111 '
b111 "
1/
06
0I
0@
1:
1D
0C
1#
0$
#630
b1000 '
b111 &
b111 !
1+
0H
16
1@
0:
0D
1C
0#
1$
#640
b0 '
b0 "
0/
0.
0-
1I
1K
1M
0>
0=
0<
1:
19
18
0C
0$
1%
#650
b1 '
b1 "
1/
0I
1>
0:
#660
b10 '
b10 "
0/
1.
1I
0K
0>
1=
1:
09
#670
b11 '
b11 "
1/
0I
1>
0:
#680
b100 '
b100 "
0/
0.
1-
1I
1K
0M
0>
0=
1<
1:
19
08
#690
b101 '
b101 "
1/
0I
1>
0:
#700
b110 '
b110 "
0/
1.
1I
0K
0>
1=
1:
09
#710
b111 '
b111 "
1/
0I
1>
0:
1C
1$
0%
#720
b1000 '
b1000 &
